LinkFusions/__init__.py
LinkFusions/accounts.py
LinkFusions/campaigns.py
LinkFusions/contacts.py
LinkFusions/encoders.py
LinkFusions/exceptions.py
LinkFusions/generics.py
LinkFusions/phone_numbers.py
LinkFusions/requestor.py
LinkFusions/templates.py
LinkFusions/test.py
LinkFusions/utils.py
LinkFusions-0.0.16.dist-info/LICENSE
LinkFusions-0.0.16.dist-info/METADATA
LinkFusions-0.0.16.dist-info/WHEEL
LinkFusions-0.0.16.dist-info/top_level.txt
LinkFusions-0.0.16.dist-info/RECORD
