Metadata-Version: 2.1
Name: LinkFusions
Version: 0.0.16
Summary: Python Library to Interface LinkFusions API
Home-page: https://github.com/CloudPR/EM-LF-Repo
Author: Cloud Custom Solutions
Author-email: UNKNOWN
License: UNKNOWN
Platform: UNKNOWN
Classifier: Programming Language :: Python :: 3
Classifier: License :: OSI Approved :: MIT License
Classifier: Operating System :: OS Independent
Requires-Dist: requests (==2.22)
Requires-Dist: curlify (==2.2.1)
